aircraftdetective/__init__.py
aircraftdetective/calculations/__init__.py
aircraftdetective/calculations/aerodynamics.py
aircraftdetective/calculations/engines.py
aircraftdetective/utility/__init__.py
aircraftdetective/utility/plotting.py
aircraftdetective/utility/statistics.py
aircraftdetective/utility/tabular.py
aircraftdetective-0.0.3.dist-info/licenses/LICENSE.txt
aircraftdetective-0.0.3.dist-info/METADATA
aircraftdetective-0.0.3.dist-info/WHEEL
aircraftdetective-0.0.3.dist-info/top_level.txt
aircraftdetective-0.0.3.dist-info/RECORD
